udos/__init__.py
udos-0.0.2.dist-info/LICENSE
udos-0.0.2.dist-info/METADATA
udos-0.0.2.dist-info/WHEEL
udos-0.0.2.dist-info/top_level.txt
udos-0.0.2.dist-info/RECORD
