Metadata-Version: 2.1
Name: udos
Version: 0.0.2
Summary: Universal Dataset Open Standard
Home-page: https://github.com/i2mint/udos
Author: OtoSense
License: apache-2.0
Platform: any
